[
    {
        "title": "ITFO_ALCH_NEW",
        "name": "Spirytus",
        "opis": "Baza mikstur i alkoholi",
        "mainFlag": "ITEM_CAT_FOOD",
        "instance": "ITFO_SDRP_ALH_01",
        "instancesaga3": "ITFO_GS_58",
        "category": "Consumable",
        "weight": "0,2",
        "durability": "BRAK",
        "uses": "2",
        "staminaPerHit": "0",
        "hpPerHit": "-2,5",
        "manaPerHit": "0",
        "stamina": "0",
        "hp": "-5",
        "mana": "0",
        "dmgType": "BRAK",
        "dmg": "BRAK",
        "range": "BRAK",
        "strength": "BRAK",
        "dexterity": "BRAK",
        "intelligence": "BRAK",
        "magicCircle": "BRAK",
        "manaCost": "BRAK",
        "resistance_blunt": "BRAK",
        "resistance_projectile": "BRAK",
        "resistance_slash": "BRAK",
        "resistance_magic": "BRAK",
        "resistance_fire": "BRAK",
        "resistance_fall": "BRAK",
        "modelNazwa": "ITFO_ALCH_NEW.3ds",
        "tier": "T0",
        "expirationTime": "32400",
        "plik": "consumable",
        "profession": "Alchemik",
        "model": "assets/models/ITFO_ALCH_NEW.glb",
        "thumbnail": "assets/card/ITFO_ALCH_NEW.webp"
    },
    {
        "title": "ITMI_POCKET",
        "name": "Pieprz",
        "opis": "Drobna przyprawa, która daje wielki smak!",
        "mainFlag": "ITEM_CAT_NONE",
        "instance": "ITFO_ADDON_PFEFFER_01",
        "instancesaga3": "ITMI_GS_MAT_72",
        "category": "Materials",
        "weight": "0,2",
        "durability": "BRAK",
        "uses": "BRAK",
        "staminaPerHit": "BRAK",
        "hpPerHit": "BRAK",
        "manaPerHit": "BRAK",
        "stamina": "BRAK",
        "hp": "BRAK",
        "mana": "BRAK",
        "dmgType": "BRAK",
        "dmg": "BRAK",
        "range": "BRAK",
        "strength": "BRAK",
        "dexterity": "BRAK",
        "intelligence": "BRAK",
        "magicCircle": "BRAK",
        "manaCost": "BRAK",
        "resistance_blunt": "BRAK",
        "resistance_projectile": "BRAK",
        "resistance_slash": "BRAK",
        "resistance_magic": "BRAK",
        "resistance_fire": "BRAK",
        "resistance_fall": "BRAK",
        "modelNazwa": "ItMi_Pocket.3ds",
        "tier": "T0",
        "expirationTime": "BRAK",
        "plik": "materials",
        "profession": "Alchemik",
        "model": "assets/models/ITMI_POCKET.glb",
        "thumbnail": "assets/card/ITMI_POCKET.webp"
    },
    {
        "title": "ITMI_ALCHEMY_SALT_01",
        "name": "Cukier",
        "opis": "Słodycze bez tego by wiele straciły.",
        "mainFlag": "ITEM_CAT_NONE",
        "instance": "ITCR_SDRP_INGR_24",
        "instancesaga3": "ITMI_GS_MAT_73",
        "category": "Materials",
        "weight": "0,2",
        "durability": "BRAK",
        "uses": "BRAK",
        "staminaPerHit": "BRAK",
        "hpPerHit": "BRAK",
        "manaPerHit": "BRAK",
        "stamina": "BRAK",
        "hp": "BRAK",
        "mana": "BRAK",
        "dmgType": "BRAK",
        "dmg": "BRAK",
        "range": "BRAK",
        "strength": "BRAK",
        "dexterity": "BRAK",
        "intelligence": "BRAK",
        "magicCircle": "BRAK",
        "manaCost": "BRAK",
        "resistance_blunt": "BRAK",
        "resistance_projectile": "BRAK",
        "resistance_slash": "BRAK",
        "resistance_magic": "BRAK",
        "resistance_fire": "BRAK",
        "resistance_fall": "BRAK",
        "modelNazwa": "ItMi_Alchemy_Salt_01.3ds",
        "tier": "T0",
        "expirationTime": "BRAK",
        "plik": "materials",
        "profession": "Alchemik",
        "model": "assets/models/ITMI_ALCHEMY_SALT_01.glb",
        "thumbnail": "assets/card/ITMI_ALCHEMY_SALT_01.webp"
    },
    {
        "title": "ITMI_ALCHEMY_MOLERATLUBRIC_01",
        "name": "Drożdze",
        "opis": "Mieszanka wody z mąką.",
        "mainFlag": "ITEM_CAT_NONE",
        "instance": "ITCR_SDRP_DROP_75",
        "instancesaga3": "ITMI_GS_MAT_74",
        "category": "Materials",
        "weight": "0,2",
        "durability": "BRAK",
        "uses": "BRAK",
        "staminaPerHit": "BRAK",
        "hpPerHit": "BRAK",
        "manaPerHit": "BRAK",
        "stamina": "BRAK",
        "hp": "BRAK",
        "mana": "BRAK",
        "dmgType": "BRAK",
        "dmg": "BRAK",
        "range": "BRAK",
        "strength": "BRAK",
        "dexterity": "BRAK",
        "intelligence": "BRAK",
        "magicCircle": "BRAK",
        "manaCost": "BRAK",
        "resistance_blunt": "BRAK",
        "resistance_projectile": "BRAK",
        "resistance_slash": "BRAK",
        "resistance_magic": "BRAK",
        "resistance_fire": "BRAK",
        "resistance_fall": "BRAK",
        "modelNazwa": "ItMi_Alchemy_Moleratlubric_01.3ds",
        "tier": "T1",
        "expirationTime": "BRAK",
        "plik": "materials",
        "profession": "Alchemik",
        "model": "assets/models/ITMI_ALCHEMY_MOLERATLUBRIC_01.glb",
        "thumbnail": "assets/card/ITMI_ALCHEMY_MOLERATLUBRIC_01.webp"
    },
    {
        "title": "ITFO_LAKOMY_BEER_01",
        "name": "Piwo portowe",
        "opis": "Prawdziwy napój portowca.",
        "mainFlag": "ITEM_CAT_FOOD",
        "instance": "ITFO_SDRP_KM_57",
        "instancesaga3": "ITFO_GS_59",
        "category": "Consumable",
        "weight": "0,2",
        "durability": "BRAK",
        "uses": "1",
        "staminaPerHit": "5",
        "hpPerHit": "1",
        "manaPerHit": "0",
        "stamina": "5",
        "hp": "1",
        "mana": "0",
        "dmgType": "BRAK",
        "dmg": "BRAK",
        "range": "BRAK",
        "strength": "BRAK",
        "dexterity": "BRAK",
        "intelligence": "BRAK",
        "magicCircle": "BRAK",
        "manaCost": "BRAK",
        "resistance_blunt": "BRAK",
        "resistance_projectile": "BRAK",
        "resistance_slash": "BRAK",
        "resistance_magic": "BRAK",
        "resistance_fire": "BRAK",
        "resistance_fall": "BRAK",
        "modelNazwa": "ItFo_Lakomy_Beer_01.3ds",
        "tier": "T1",
        "expirationTime": "32400",
        "plik": "consumable",
        "profession": "Alchemik",
        "model": "assets/models/ITFO_LAKOMY_BEER_01.glb",
        "thumbnail": "assets/card/ITFO_LAKOMY_BEER_01.webp"
    },
    {
        "title": "APFELSAFT",
        "name": "Jabol",
        "opis": "Przysmak okolicznych wsi.",
        "mainFlag": "ITEM_CAT_FOOD",
        "instance": "ITFO_SDRP_ALH_03",
        "instancesaga3": "ITFO_GS_60",
        "category": "Consumable",
        "weight": "0,2",
        "durability": "BRAK",
        "uses": "3",
        "staminaPerHit": "4",
        "hpPerHit": "1",
        "manaPerHit": "0",
        "stamina": "12",
        "hp": "3",
        "mana": "0",
        "dmgType": "BRAK",
        "dmg": "BRAK",
        "range": "BRAK",
        "strength": "BRAK",
        "dexterity": "BRAK",
        "intelligence": "BRAK",
        "magicCircle": "BRAK",
        "manaCost": "BRAK",
        "resistance_blunt": "BRAK",
        "resistance_projectile": "BRAK",
        "resistance_slash": "BRAK",
        "resistance_magic": "BRAK",
        "resistance_fire": "BRAK",
        "resistance_fall": "BRAK",
        "modelNazwa": "APFELSAFT.3ds",
        "tier": "T1",
        "expirationTime": "32400",
        "plik": "consumable",
        "profession": "Alchemik",
        "model": "assets/models/APFELSAFT.glb",
        "thumbnail": "assets/card/APFELSAFT.webp"
    },
    {
        "title": "BEERENLIKOER",
        "name": "Nalewka Jagodowa",
        "opis": "Słodki alkohol o rubinowej barwie.",
        "mainFlag": "ITEM_CAT_FOOD",
        "instance": "ITFO_SDRP_ALH_06",
        "instancesaga3": "ITFO_GS_61",
        "category": "Consumable",
        "weight": "0,2",
        "durability": "BRAK",
        "uses": "3",
        "staminaPerHit": "6",
        "hpPerHit": "1",
        "manaPerHit": "0",
        "stamina": "18",
        "hp": "3",
        "mana": "0",
        "dmgType": "BRAK",
        "dmg": "BRAK",
        "range": "BRAK",
        "strength": "BRAK",
        "dexterity": "BRAK",
        "intelligence": "BRAK",
        "magicCircle": "BRAK",
        "manaCost": "BRAK",
        "resistance_blunt": "BRAK",
        "resistance_projectile": "BRAK",
        "resistance_slash": "BRAK",
        "resistance_magic": "BRAK",
        "resistance_fire": "BRAK",
        "resistance_fall": "BRAK",
        "modelNazwa": "BEERENLIKOER.3ds",
        "tier": "T2",
        "expirationTime": "32400",
        "plik": "consumable",
        "profession": "Alchemik",
        "model": "assets/models/BEERENLIKOER.glb",
        "thumbnail": "assets/card/BEERENLIKOER.webp"
    },
    {
        "title": "KM_VOB_DARKBEER",
        "name": "Piwo pszeniczne",
        "opis": "Podawane w każdej myrtańskiej karczmie.",
        "mainFlag": "ITEM_CAT_FOOD",
        "instance": "ITFO_SDRP_KM_14",
        "instancesaga3": "ITFO_GS_62",
        "category": "Consumable",
        "weight": "0,2",
        "durability": "BRAK",
        "uses": "2",
        "staminaPerHit": "5",
        "hpPerHit": "1",
        "manaPerHit": "0",
        "stamina": "10",
        "hp": "2",
        "mana": "0",
        "dmgType": "BRAK",
        "dmg": "BRAK",
        "range": "BRAK",
        "strength": "BRAK",
        "dexterity": "BRAK",
        "intelligence": "BRAK",
        "magicCircle": "BRAK",
        "manaCost": "BRAK",
        "resistance_blunt": "BRAK",
        "resistance_projectile": "BRAK",
        "resistance_slash": "BRAK",
        "resistance_magic": "BRAK",
        "resistance_fire": "BRAK",
        "resistance_fall": "BRAK",
        "modelNazwa": "KM_vob_darkbeer.3ds",
        "tier": "T2",
        "expirationTime": "32400",
        "plik": "consumable",
        "profession": "Alchemik",
        "model": "assets/models/KM_VOB_DARKBEER.glb",
        "thumbnail": "assets/card/KM_VOB_DARKBEER.webp"
    },
    {
        "title": "ITFO_WINE",
        "name": "Wino",
        "opis": "Z delikatnym smakiem, stworzone z myślą o wysublinowanym smaku",
        "mainFlag": "ITEM_CAT_FOOD",
        "instance": "ITFO_WINE",
        "instancesaga3": "ITFO_GS_63",
        "category": "Consumable",
        "weight": "0,2",
        "durability": "BRAK",
        "uses": "4",
        "staminaPerHit": "4",
        "hpPerHit": "1",
        "manaPerHit": "0",
        "stamina": "16",
        "hp": "4",
        "mana": "0",
        "dmgType": "BRAK",
        "dmg": "BRAK",
        "range": "BRAK",
        "strength": "BRAK",
        "dexterity": "BRAK",
        "intelligence": "BRAK",
        "magicCircle": "BRAK",
        "manaCost": "BRAK",
        "resistance_blunt": "BRAK",
        "resistance_projectile": "BRAK",
        "resistance_slash": "BRAK",
        "resistance_magic": "BRAK",
        "resistance_fire": "BRAK",
        "resistance_fall": "BRAK",
        "modelNazwa": "ItFo_Wine.3ds",
        "tier": "T2",
        "expirationTime": "32400",
        "plik": "consumable",
        "profession": "Alchemik",
        "model": "assets/models/ITFO_WINE.glb",
        "thumbnail": "assets/card/ITFO_WINE.webp"
    },
    {
        "title": "KM_NEW_BOTTLE_02",
        "name": "Wóda Ziołowa",
        "opis": "Alkohol powstały wyłącznie z fermentacji ziół.",
        "mainFlag": "ITEM_CAT_FOOD",
        "instance": "ITFO_SDRP_KM_59",
        "instancesaga3": "ITFO_GS_64",
        "category": "Consumable",
        "weight": "0,2",
        "durability": "BRAK",
        "uses": "2",
        "staminaPerHit": "12,5",
        "hpPerHit": "2,5",
        "manaPerHit": "0",
        "stamina": "25",
        "hp": "5",
        "mana": "0",
        "dmgType": "BRAK",
        "dmg": "BRAK",
        "range": "BRAK",
        "strength": "BRAK",
        "dexterity": "BRAK",
        "intelligence": "BRAK",
        "magicCircle": "BRAK",
        "manaCost": "BRAK",
        "resistance_blunt": "BRAK",
        "resistance_projectile": "BRAK",
        "resistance_slash": "BRAK",
        "resistance_magic": "BRAK",
        "resistance_fire": "BRAK",
        "resistance_fall": "BRAK",
        "modelNazwa": "KM_new_bottle_02.3ds",
        "tier": "T3",
        "expirationTime": "32400",
        "plik": "consumable",
        "profession": "Alchemik",
        "model": "assets/models/KM_NEW_BOTTLE_02.glb",
        "thumbnail": "assets/card/KM_NEW_BOTTLE_02.webp"
    },
    {
        "title": "KM_NEW_BOTTLE_09",
        "name": "Piwo Miodowe",
        "opis": "Specjalne piwo z dodatkiem miodu.",
        "mainFlag": "ITEM_CAT_FOOD",
        "instance": "ITFO_SDRP_KM_08",
        "instancesaga3": "ITFO_GS_65",
        "category": "Consumable",
        "weight": "0,2",
        "durability": "BRAK",
        "uses": "2",
        "staminaPerHit": "10",
        "hpPerHit": "1",
        "manaPerHit": "0",
        "stamina": "20",
        "hp": "2",
        "mana": "0",
        "dmgType": "BRAK",
        "dmg": "BRAK",
        "range": "BRAK",
        "strength": "BRAK",
        "dexterity": "BRAK",
        "intelligence": "BRAK",
        "magicCircle": "BRAK",
        "manaCost": "BRAK",
        "resistance_blunt": "BRAK",
        "resistance_projectile": "BRAK",
        "resistance_slash": "BRAK",
        "resistance_magic": "BRAK",
        "resistance_fire": "BRAK",
        "resistance_fall": "BRAK",
        "modelNazwa": "KM_new_bottle_09.3ds",
        "tier": "T3",
        "expirationTime": "32400",
        "plik": "consumable",
        "profession": "Alchemik",
        "model": "assets/models/KM_NEW_BOTTLE_09.glb",
        "thumbnail": "assets/card/KM_NEW_BOTTLE_09.webp"
    },
    {
        "title": "TRAUBENSAFT",
        "name": "Gin",
        "opis": "Bardzo popularny alkohol na kontynencie.",
        "mainFlag": "ITEM_CAT_FOOD",
        "instance": "ITFO_SDRP_ALH_13",
        "instancesaga3": "ITFO_GS_66",
        "category": "Consumable",
        "weight": "0,2",
        "durability": "BRAK",
        "uses": "5",
        "staminaPerHit": "7",
        "hpPerHit": "1",
        "manaPerHit": "0",
        "stamina": "35",
        "hp": "5",
        "mana": "0",
        "dmgType": "BRAK",
        "dmg": "BRAK",
        "range": "BRAK",
        "strength": "BRAK",
        "dexterity": "BRAK",
        "intelligence": "BRAK",
        "magicCircle": "BRAK",
        "manaCost": "BRAK",
        "resistance_blunt": "BRAK",
        "resistance_projectile": "BRAK",
        "resistance_slash": "BRAK",
        "resistance_magic": "BRAK",
        "resistance_fire": "BRAK",
        "resistance_fall": "BRAK",
        "modelNazwa": "TRAUBENSAFT.3ds",
        "tier": "T4",
        "expirationTime": "32400",
        "plik": "consumable",
        "profession": "Alchemik",
        "model": "assets/models/TRAUBENSAFT.glb",
        "thumbnail": "assets/card/TRAUBENSAFT.webp"
    },
    {
        "title": "ITMI_RUM_02",
        "name": "Rum",
        "opis": "Mocny i słodki napój alkoholowy",
        "mainFlag": "ITEM_CAT_FOOD",
        "instance": "ITFO_ADDON_RUM",
        "instancesaga3": "ITFO_GS_67",
        "category": "Consumable",
        "weight": "0,2",
        "durability": "BRAK",
        "uses": "2",
        "staminaPerHit": "12,5",
        "hpPerHit": "3",
        "manaPerHit": "0",
        "stamina": "25",
        "hp": "6",
        "mana": "0",
        "dmgType": "BRAK",
        "dmg": "BRAK",
        "range": "BRAK",
        "strength": "BRAK",
        "dexterity": "BRAK",
        "intelligence": "BRAK",
        "magicCircle": "BRAK",
        "manaCost": "BRAK",
        "resistance_blunt": "BRAK",
        "resistance_projectile": "BRAK",
        "resistance_slash": "BRAK",
        "resistance_magic": "BRAK",
        "resistance_fire": "BRAK",
        "resistance_fall": "BRAK",
        "modelNazwa": "ItMi_Rum_02.3ds",
        "tier": "T4",
        "expirationTime": "32400",
        "plik": "consumable",
        "profession": "Alchemik",
        "model": "assets/models/ITMI_RUM_02.glb",
        "thumbnail": "assets/card/ITMI_RUM_02.webp"
    },
    {
        "title": "ITMI_RUM_01",
        "name": "Szybki Śledź",
        "opis": "Niebezpieczny i tajemniczy zabójca, który działa szybko i bezlitośnie.",
        "mainFlag": "ITEM_CAT_FOOD",
        "instance": "ITFO_ADDON_SCHNELLERHERING",
        "instancesaga3": "ITFO_GS_68",
        "category": "Consumable",
        "weight": "0,2",
        "durability": "BRAK",
        "uses": "4",
        "staminaPerHit": "10",
        "hpPerHit": "3",
        "manaPerHit": "2,5",
        "stamina": "40",
        "hp": "12",
        "mana": "10",
        "dmgType": "BRAK",
        "dmg": "BRAK",
        "range": "BRAK",
        "strength": "BRAK",
        "dexterity": "BRAK",
        "intelligence": "BRAK",
        "magicCircle": "BRAK",
        "manaCost": "BRAK",
        "resistance_blunt": "BRAK",
        "resistance_projectile": "BRAK",
        "resistance_slash": "BRAK",
        "resistance_magic": "BRAK",
        "resistance_fire": "BRAK",
        "resistance_fall": "BRAK",
        "modelNazwa": "ItMi_Rum_01.3ds",
        "tier": "T5",
        "expirationTime": "32400",
        "plik": "consumable",
        "profession": "Alchemik",
        "model": "assets/models/ITMI_RUM_01.glb",
        "thumbnail": "assets/card/ITMI_RUM_01.webp"
    },
    {
        "title": "ITMI_RUM_01",
        "name": "Młot Lou",
        "opis": "Potężna trunek, która może zmiażdżyć wszystko na swojej drodze",
        "mainFlag": "ITEM_CAT_FOOD",
        "instance": "ITFO_ADDON_SCHNELLERHERING",
        "instancesaga3": "ITFO_GS_69",
        "category": "Consumable",
        "weight": "0,2",
        "durability": "BRAK",
        "uses": "2",
        "staminaPerHit": "20",
        "hpPerHit": "6",
        "manaPerHit": "5",
        "stamina": "40",
        "hp": "12",
        "mana": "10",
        "dmgType": "BRAK",
        "dmg": "BRAK",
        "range": "BRAK",
        "strength": "BRAK",
        "dexterity": "BRAK",
        "intelligence": "BRAK",
        "magicCircle": "BRAK",
        "manaCost": "BRAK",
        "resistance_blunt": "BRAK",
        "resistance_projectile": "BRAK",
        "resistance_slash": "BRAK",
        "resistance_magic": "BRAK",
        "resistance_fire": "BRAK",
        "resistance_fall": "BRAK",
        "modelNazwa": "ItMi_Rum_01.3ds",
        "tier": "T5",
        "expirationTime": "32400",
        "plik": "consumable",
        "profession": "Alchemik",
        "model": "assets/models/ITMI_RUM_01.glb",
        "thumbnail": "assets/card/ITMI_RUM_01.webp"
    },
    {
        "title": "ITMI_JOINT_US",
        "name": "Skręt z bagiennego ziela",
        "opis": "Palenie łodyg bagiennego ziela to najbardziej popularna forma zażywania narkotyku. Ze względu na ich właściwości halucynogenne i relaksujące są one zakazane.",
        "mainFlag": "ITEM_CAT_POTION",
        "instance": "ITMI_JOINT",
        "instancesaga3": "ITPO_GS_01",
        "category": "Consumable",
        "weight": "0,05",
        "durability": "BRAK",
        "uses": "1",
        "staminaPerHit": "0",
        "hpPerHit": "0",
        "manaPerHit": "15",
        "stamina": "0",
        "hp": "0",
        "mana": "15",
        "dmgType": "BRAK",
        "dmg": "BRAK",
        "range": "BRAK",
        "strength": "BRAK",
        "dexterity": "BRAK",
        "intelligence": "BRAK",
        "magicCircle": "BRAK",
        "manaCost": "BRAK",
        "resistance_blunt": "BRAK",
        "resistance_projectile": "BRAK",
        "resistance_slash": "BRAK",
        "resistance_magic": "BRAK",
        "resistance_fire": "BRAK",
        "resistance_fall": "BRAK",
        "modelNazwa": "ItMi_Joint_US.3ds",
        "tier": "T1",
        "expirationTime": "BRAK",
        "plik": "consumable",
        "profession": "Alchemik",
        "model": "assets/models/ITMI_JOINT_US.glb",
        "thumbnail": "assets/card/ITMI_JOINT_US.webp"
    },
    {
        "title": "STATIC_JOINT_ZAUCHEM",
        "name": "Skręt zza uchem",
        "opis": "Skręt zza uchem",
        "mainFlag": "ITEM_CAT_ACSR1",
        "instance": "ITUS_SDRP_ACS_17",
        "instancesaga3": "ITAC_GS_ACSR1_01",
        "category": "AccessorySlot1",
        "weight": "0,05",
        "durability": "BRAK",
        "uses": "BRAK",
        "staminaPerHit": "BRAK",
        "hpPerHit": "BRAK",
        "manaPerHit": "BRAK",
        "stamina": "BRAK",
        "hp": "BRAK",
        "mana": "BRAK",
        "dmgType": "BRAK",
        "dmg": "BRAK",
        "range": "BRAK",
        "strength": "BRAK",
        "dexterity": "BRAK",
        "intelligence": "BRAK",
        "magicCircle": "BRAK",
        "manaCost": "BRAK",
        "resistance_blunt": "BRAK",
        "resistance_projectile": "BRAK",
        "resistance_slash": "BRAK",
        "resistance_magic": "BRAK",
        "resistance_fire": "BRAK",
        "resistance_fall": "BRAK",
        "modelNazwa": "STATIC_joint_zauchem.3ds",
        "tier": "T1",
        "expirationTime": "BRAK",
        "plik": "acsr1",
        "profession": "Alchemik",
        "model": "assets/models/STATIC_JOINT_ZAUCHEM.glb",
        "thumbnail": "assets/card/STATIC_JOINT_ZAUCHEM.webp"
    },
    {
        "title": "STATIC_SKRET_USTA1",
        "name": "Skręt w ustach",
        "opis": "Skręt trzymany w zębach",
        "mainFlag": "ITEM_CAT_ACSR2",
        "instance": "ITUS_SDRP_ACS_18",
        "instancesaga3": "ITAC_GS_ACSR2_01",
        "category": "AccessorySlot2",
        "weight": "0,05",
        "durability": "BRAK",
        "uses": "BRAK",
        "staminaPerHit": "BRAK",
        "hpPerHit": "BRAK",
        "manaPerHit": "BRAK",
        "stamina": "BRAK",
        "hp": "BRAK",
        "mana": "BRAK",
        "dmgType": "BRAK",
        "dmg": "BRAK",
        "range": "BRAK",
        "strength": "BRAK",
        "dexterity": "BRAK",
        "intelligence": "BRAK",
        "magicCircle": "BRAK",
        "manaCost": "BRAK",
        "resistance_blunt": "BRAK",
        "resistance_projectile": "BRAK",
        "resistance_slash": "BRAK",
        "resistance_magic": "BRAK",
        "resistance_fire": "BRAK",
        "resistance_fall": "BRAK",
        "modelNazwa": "STATIC_skret_usta1.3ds",
        "tier": "T1",
        "expirationTime": "BRAK",
        "plik": "acsr2",
        "profession": "Alchemik",
        "model": "assets/models/STATIC_SKRET_USTA1.glb",
        "thumbnail": "assets/card/STATIC_SKRET_USTA1.webp"
    },
    {
        "title": "FAJA2",
        "name": "Grzybowy skręt",
        "opis": "Delikatny skręcik z nutką grzybów.",
        "mainFlag": "ITEM_CAT_POTION",
        "instance": "faja2",
        "instancesaga3": "ITPO_GS_02",
        "category": "Consumable",
        "weight": "0,05",
        "durability": "BRAK",
        "uses": "1",
        "staminaPerHit": "0",
        "hpPerHit": "0",
        "manaPerHit": "25",
        "stamina": "0",
        "hp": "0",
        "mana": "25",
        "dmgType": "BRAK",
        "dmg": "BRAK",
        "range": "BRAK",
        "strength": "BRAK",
        "dexterity": "BRAK",
        "intelligence": "BRAK",
        "magicCircle": "BRAK",
        "manaCost": "BRAK",
        "resistance_blunt": "BRAK",
        "resistance_projectile": "BRAK",
        "resistance_slash": "BRAK",
        "resistance_magic": "BRAK",
        "resistance_fire": "BRAK",
        "resistance_fall": "BRAK",
        "modelNazwa": "faja2.3ds",
        "tier": "T2",
        "expirationTime": "BRAK",
        "plik": "consumable",
        "profession": "Alchemik",
        "model": "assets/models/FAJA2.glb",
        "thumbnail": "assets/card/FAJA2.webp"
    },
    {
        "title": "FAJA3",
        "name": "Jabłkowy skręt",
        "opis": "Aromatyczny skret z dodatkiem jabłek.",
        "mainFlag": "ITEM_CAT_POTION",
        "instance": "faja3",
        "instancesaga3": "ITPO_GS_03",
        "category": "Consumable",
        "weight": "0,05",
        "durability": "BRAK",
        "uses": "1",
        "staminaPerHit": "0",
        "hpPerHit": "0",
        "manaPerHit": "25",
        "stamina": "0",
        "hp": "0",
        "mana": "25",
        "dmgType": "BRAK",
        "dmg": "BRAK",
        "range": "BRAK",
        "strength": "BRAK",
        "dexterity": "BRAK",
        "intelligence": "BRAK",
        "magicCircle": "BRAK",
        "manaCost": "BRAK",
        "resistance_blunt": "BRAK",
        "resistance_projectile": "BRAK",
        "resistance_slash": "BRAK",
        "resistance_magic": "BRAK",
        "resistance_fire": "BRAK",
        "resistance_fall": "BRAK",
        "modelNazwa": "faja3.3ds",
        "tier": "T2",
        "expirationTime": "BRAK",
        "plik": "consumable",
        "profession": "Alchemik",
        "model": "assets/models/FAJA3.glb",
        "thumbnail": "assets/card/FAJA3.webp"
    },
    {
        "title": "GS_URNALESTERA",
        "name": "Miodowy skręt",
        "opis": "Słodki i aromatyczny skręt, który może być zarówno kojący, jak i odurzający.",
        "mainFlag": "ITEM_CAT_POTION",
        "instance": "GS_URNALESTERA",
        "instancesaga3": "ITPO_GS_04",
        "category": "Consumable",
        "weight": "0,05",
        "durability": "BRAK",
        "uses": "2",
        "staminaPerHit": "0",
        "hpPerHit": "0",
        "manaPerHit": "25",
        "stamina": "0",
        "hp": "0",
        "mana": "50",
        "dmgType": "BRAK",
        "dmg": "BRAK",
        "range": "BRAK",
        "strength": "BRAK",
        "dexterity": "BRAK",
        "intelligence": "BRAK",
        "magicCircle": "BRAK",
        "manaCost": "BRAK",
        "resistance_blunt": "BRAK",
        "resistance_projectile": "BRAK",
        "resistance_slash": "BRAK",
        "resistance_magic": "BRAK",
        "resistance_fire": "BRAK",
        "resistance_fall": "BRAK",
        "modelNazwa": "GS_URNALESTERA.3ds",
        "tier": "T3",
        "expirationTime": "BRAK",
        "plik": "consumable",
        "profession": "Alchemik",
        "model": "assets/models/GS_URNALESTERA.glb",
        "thumbnail": "assets/card/GS_URNALESTERA.webp"
    },
    {
        "title": "FAKESCROLL",
        "name": "Papirus",
        "opis": "Ma wiele zastosowań zarówno wśród poetów jak i magów.",
        "mainFlag": "ITEM_CAT_NONE",
        "instance": "FAKESCROLL_ADDON",
        "instancesaga3": "ITMI_GS_MAT_75",
        "category": "Materials",
        "weight": "0,1",
        "durability": "BRAK",
        "uses": "BRAK",
        "staminaPerHit": "BRAK",
        "hpPerHit": "BRAK",
        "manaPerHit": "BRAK",
        "stamina": "BRAK",
        "hp": "BRAK",
        "mana": "BRAK",
        "dmgType": "BRAK",
        "dmg": "BRAK",
        "range": "BRAK",
        "strength": "BRAK",
        "dexterity": "BRAK",
        "intelligence": "BRAK",
        "magicCircle": "BRAK",
        "manaCost": "BRAK",
        "resistance_blunt": "BRAK",
        "resistance_projectile": "BRAK",
        "resistance_slash": "BRAK",
        "resistance_magic": "BRAK",
        "resistance_fire": "BRAK",
        "resistance_fall": "BRAK",
        "modelNazwa": "Fakescroll.3ds",
        "tier": "T0",
        "expirationTime": "BRAK",
        "plik": "materials",
        "profession": "Alchemik",
        "model": "assets/models/FAKESCROLL.glb",
        "thumbnail": "assets/card/FAKESCROLL.webp"
    },
    {
        "title": "ITPO_HEALTH_01",
        "name": "Esencja lecznicza",
        "opis": "Jedna z mikstur leczących",
        "mainFlag": "ITEM_CAT_POTION",
        "instance": "ItPo_Health_01",
        "instancesaga3": "ITPO_GS_05",
        "category": "Potion",
        "weight": "0,2",
        "durability": "BRAK",
        "uses": "1",
        "staminaPerHit": "0",
        "hpPerHit": "15",
        "manaPerHit": "0",
        "stamina": "0",
        "hp": "15",
        "mana": "0",
        "dmgType": "BRAK",
        "dmg": "BRAK",
        "range": "BRAK",
        "strength": "BRAK",
        "dexterity": "BRAK",
        "intelligence": "BRAK",
        "magicCircle": "BRAK",
        "manaCost": "BRAK",
        "resistance_blunt": "BRAK",
        "resistance_projectile": "BRAK",
        "resistance_slash": "BRAK",
        "resistance_magic": "BRAK",
        "resistance_fire": "BRAK",
        "resistance_fall": "BRAK",
        "modelNazwa": "ItPo_Health_01.3ds",
        "tier": "T1",
        "expirationTime": "BRAK",
        "plik": "potions",
        "profession": "Alchemik",
        "model": "assets/models/ITPO_HEALTH_01.glb",
        "thumbnail": "assets/card/ITPO_HEALTH_01.webp"
    },
    {
        "title": "ITPO_MANA_01",
        "name": "Esencja many",
        "opis": "Jedna z mikstur odnawiających energię duchową",
        "mainFlag": "ITEM_CAT_POTION",
        "instance": "ItPo_Mana_01",
        "instancesaga3": "ITPO_GS_06",
        "category": "Potion",
        "weight": "0,2",
        "durability": "BRAK",
        "uses": "1",
        "staminaPerHit": "0",
        "hpPerHit": "0",
        "manaPerHit": "15",
        "stamina": "0",
        "hp": "0",
        "mana": "15",
        "dmgType": "BRAK",
        "dmg": "BRAK",
        "range": "BRAK",
        "strength": "BRAK",
        "dexterity": "BRAK",
        "intelligence": "BRAK",
        "magicCircle": "BRAK",
        "manaCost": "BRAK",
        "resistance_blunt": "BRAK",
        "resistance_projectile": "BRAK",
        "resistance_slash": "BRAK",
        "resistance_magic": "BRAK",
        "resistance_fire": "BRAK",
        "resistance_fall": "BRAK",
        "modelNazwa": "ItPo_Mana_01.3ds",
        "tier": "T1",
        "expirationTime": "BRAK",
        "plik": "potions",
        "profession": "Alchemik",
        "model": "assets/models/ITPO_MANA_01.glb",
        "thumbnail": "assets/card/ITPO_MANA_01.webp"
    },
    {
        "title": "FRUCHTSCHNAPS",
        "name": "Odwar garbarski",
        "opis": "Używana do garbowania skór przez myśliwych.",
        "mainFlag": "ITEM_CAT_NONE",
        "instance": "ITFO_SDRP_DSH_45",
        "instancesaga3": "ITMI_GS_MAT_76",
        "category": "Materials",
        "weight": "0,2",
        "durability": "BRAK",
        "uses": "BRAK",
        "staminaPerHit": "BRAK",
        "hpPerHit": "BRAK",
        "manaPerHit": "BRAK",
        "stamina": "BRAK",
        "hp": "BRAK",
        "mana": "BRAK",
        "dmgType": "BRAK",
        "dmg": "BRAK",
        "range": "BRAK",
        "strength": "BRAK",
        "dexterity": "BRAK",
        "intelligence": "BRAK",
        "magicCircle": "BRAK",
        "manaCost": "BRAK",
        "resistance_blunt": "BRAK",
        "resistance_projectile": "BRAK",
        "resistance_slash": "BRAK",
        "resistance_magic": "BRAK",
        "resistance_fire": "BRAK",
        "resistance_fall": "BRAK",
        "modelNazwa": "FRUCHTSCHNAPS.3ds",
        "tier": "T2",
        "expirationTime": "BRAK",
        "plik": "materials",
        "profession": "Alchemik",
        "model": "assets/models/FRUCHTSCHNAPS.glb",
        "thumbnail": "assets/card/FRUCHTSCHNAPS.webp"
    },
    {
        "title": "ITPO_HEALTH_02",
        "name": "Ekstrakt leczniczy",
        "opis": "Jedna z mikstur leczących",
        "mainFlag": "ITEM_CAT_POTION",
        "instance": "itpo_health_02",
        "instancesaga3": "ITPO_GS_07",
        "category": "Potion",
        "weight": "0,2",
        "durability": "BRAK",
        "uses": "1",
        "staminaPerHit": "0",
        "hpPerHit": "25",
        "manaPerHit": "0",
        "stamina": "0",
        "hp": "25",
        "mana": "0",
        "dmgType": "BRAK",
        "dmg": "BRAK",
        "range": "BRAK",
        "strength": "BRAK",
        "dexterity": "BRAK",
        "intelligence": "BRAK",
        "magicCircle": "BRAK",
        "manaCost": "BRAK",
        "resistance_blunt": "BRAK",
        "resistance_projectile": "BRAK",
        "resistance_slash": "BRAK",
        "resistance_magic": "BRAK",
        "resistance_fire": "BRAK",
        "resistance_fall": "BRAK",
        "modelNazwa": "ItPo_Health_02.3ds",
        "tier": "T2",
        "expirationTime": "BRAK",
        "plik": "potions",
        "profession": "Alchemik",
        "model": "assets/models/ITPO_HEALTH_02.glb",
        "thumbnail": "assets/card/ITPO_HEALTH_02.webp"
    },
    {
        "title": "ITPO_MANA_02",
        "name": "Ekstrakt many",
        "opis": "Jedna z mikstur odnawiających energię duchową",
        "mainFlag": "ITEM_CAT_POTION",
        "instance": "ItPo_Mana_02",
        "instancesaga3": "ITPO_GS_08",
        "category": "Potion",
        "weight": "0,2",
        "durability": "BRAK",
        "uses": "1",
        "staminaPerHit": "0",
        "hpPerHit": "0",
        "manaPerHit": "25",
        "stamina": "0",
        "hp": "0",
        "mana": "25",
        "dmgType": "BRAK",
        "dmg": "BRAK",
        "range": "BRAK",
        "strength": "BRAK",
        "dexterity": "BRAK",
        "intelligence": "BRAK",
        "magicCircle": "BRAK",
        "manaCost": "BRAK",
        "resistance_blunt": "BRAK",
        "resistance_projectile": "BRAK",
        "resistance_slash": "BRAK",
        "resistance_magic": "BRAK",
        "resistance_fire": "BRAK",
        "resistance_fall": "BRAK",
        "modelNazwa": "ItPo_Mana_02.3ds",
        "tier": "T2",
        "expirationTime": "BRAK",
        "plik": "potions",
        "profession": "Alchemik",
        "model": "assets/models/ITPO_MANA_02.glb",
        "thumbnail": "assets/card/ITPO_MANA_02.webp"
    },
    {
        "title": "ITAC_EMPTY_SMALL",
        "name": "Odtrutka",
        "opis": "Mikstura neutralizująca działanie trucizny.",
        "mainFlag": "ITEM_CAT_POTION",
        "instance": "ITCR_SDRP_MED_25",
        "instancesaga3": "ITPO_GS_09",
        "category": "Potion",
        "weight": "0,2",
        "durability": "BRAK",
        "uses": "1",
        "staminaPerHit": "0",
        "hpPerHit": "0",
        "manaPerHit": "0",
        "stamina": "0",
        "hp": "0",
        "mana": "0",
        "dmgType": "BRAK",
        "dmg": "BRAK",
        "range": "BRAK",
        "strength": "BRAK",
        "dexterity": "BRAK",
        "intelligence": "BRAK",
        "magicCircle": "BRAK",
        "manaCost": "BRAK",
        "resistance_blunt": "BRAK",
        "resistance_projectile": "BRAK",
        "resistance_slash": "BRAK",
        "resistance_magic": "BRAK",
        "resistance_fire": "BRAK",
        "resistance_fall": "BRAK",
        "modelNazwa": "ITAC_EMPTY_SMALL.3ds",
        "tier": "T2",
        "expirationTime": "BRAK",
        "plik": "potions",
        "profession": "Alchemik",
        "model": "assets/models/ITAC_EMPTY_SMALL.glb",
        "thumbnail": "assets/card/ITAC_EMPTY_SMALL.webp"
    },
    {
        "title": "MINZSCHNAPS",
        "name": "Barwniki",
        "opis": "Dzięki barwnikom twoje ubrania mają pożądany kolor",
        "mainFlag": "ITEM_CAT_NONE",
        "instance": "ITCR_SDRP_MED_14",
        "instancesaga3": "ITMI_GS_MAT_77",
        "category": "Materials",
        "weight": "0,2",
        "durability": "BRAK",
        "uses": "BRAK",
        "staminaPerHit": "BRAK",
        "hpPerHit": "BRAK",
        "manaPerHit": "BRAK",
        "stamina": "BRAK",
        "hp": "BRAK",
        "mana": "BRAK",
        "dmgType": "BRAK",
        "dmg": "BRAK",
        "range": "BRAK",
        "strength": "BRAK",
        "dexterity": "BRAK",
        "intelligence": "BRAK",
        "magicCircle": "BRAK",
        "manaCost": "BRAK",
        "resistance_blunt": "BRAK",
        "resistance_projectile": "BRAK",
        "resistance_slash": "BRAK",
        "resistance_magic": "BRAK",
        "resistance_fire": "BRAK",
        "resistance_fall": "BRAK",
        "modelNazwa": "MINZSCHNAPS.3ds",
        "tier": "T2",
        "expirationTime": "BRAK",
        "plik": "materials",
        "profession": "Alchemik",
        "model": "assets/models/MINZSCHNAPS.glb",
        "thumbnail": "assets/card/MINZSCHNAPS.webp"
    },
    {
        "title": "ITFO_POTION_DEX_02",
        "name": "Eliksir Pięściarza",
        "opis": "Używana do fingowania wszelakich walk w Myrtańskim półświatku pięściarskim.",
        "mainFlag": "ITEM_CAT_POTION",
        "instance": "ITCR_SDRP_MED_10",
        "instancesaga3": "ITPO_GS_10",
        "category": "Potion",
        "weight": "0,2",
        "durability": "BRAK",
        "uses": "1",
        "staminaPerHit": "0",
        "hpPerHit": "0",
        "manaPerHit": "0",
        "stamina": "0",
        "hp": "0",
        "mana": "0",
        "dmgType": "BRAK",
        "dmg": "BRAK",
        "range": "BRAK",
        "strength": "BRAK",
        "dexterity": "BRAK",
        "intelligence": "BRAK",
        "magicCircle": "BRAK",
        "manaCost": "BRAK",
        "resistance_blunt": "BRAK",
        "resistance_projectile": "BRAK",
        "resistance_slash": "BRAK",
        "resistance_magic": "BRAK",
        "resistance_fire": "BRAK",
        "resistance_fall": "BRAK",
        "modelNazwa": "itfo_potion_dex_02.3ds",
        "tier": "T5",
        "expirationTime": "BRAK",
        "plik": "potions",
        "profession": "Alchemik",
        "model": "assets/models/ITFO_POTION_DEX_02.glb",
        "thumbnail": "assets/card/ITFO_POTION_DEX_02.webp"
    },
    {
        "title": "ITPO_HEALTH_03",
        "name": "Eliksir leczniczy",
        "opis": "Jedna z mikstur leczących",
        "mainFlag": "ITEM_CAT_POTION",
        "instance": "itpo_health_03",
        "instancesaga3": "ITPO_GS_11",
        "category": "Potion",
        "weight": "0,2",
        "durability": "BRAK",
        "uses": "1",
        "staminaPerHit": "0",
        "hpPerHit": "50",
        "manaPerHit": "0",
        "stamina": "0",
        "hp": "50",
        "mana": "0",
        "dmgType": "BRAK",
        "dmg": "BRAK",
        "range": "BRAK",
        "strength": "BRAK",
        "dexterity": "BRAK",
        "intelligence": "BRAK",
        "magicCircle": "BRAK",
        "manaCost": "BRAK",
        "resistance_blunt": "BRAK",
        "resistance_projectile": "BRAK",
        "resistance_slash": "BRAK",
        "resistance_magic": "BRAK",
        "resistance_fire": "BRAK",
        "resistance_fall": "BRAK",
        "modelNazwa": "ItPo_Health_03.3ds",
        "tier": "T3",
        "expirationTime": "BRAK",
        "plik": "potions",
        "profession": "Alchemik",
        "model": "assets/models/ITPO_HEALTH_03.glb",
        "thumbnail": "assets/card/ITPO_HEALTH_03.webp"
    },
    {
        "title": "ITPO_MANA_03",
        "name": "Eliksir many",
        "opis": "Jedna z mikstur odnawiających energię duchową",
        "mainFlag": "ITEM_CAT_POTION",
        "instance": "ItPo_Mana_03",
        "instancesaga3": "ITPO_GS_12",
        "category": "Potion",
        "weight": "0,2",
        "durability": "BRAK",
        "uses": "1",
        "staminaPerHit": "0",
        "hpPerHit": "0",
        "manaPerHit": "50",
        "stamina": "0",
        "hp": "0",
        "mana": "50",
        "dmgType": "BRAK",
        "dmg": "BRAK",
        "range": "BRAK",
        "strength": "BRAK",
        "dexterity": "BRAK",
        "intelligence": "BRAK",
        "magicCircle": "BRAK",
        "manaCost": "BRAK",
        "resistance_blunt": "BRAK",
        "resistance_projectile": "BRAK",
        "resistance_slash": "BRAK",
        "resistance_magic": "BRAK",
        "resistance_fire": "BRAK",
        "resistance_fall": "BRAK",
        "modelNazwa": "ItPo_Mana_03.3ds",
        "tier": "T3",
        "expirationTime": "BRAK",
        "plik": "potions",
        "profession": "Alchemik",
        "model": "assets/models/ITPO_MANA_03.glb",
        "thumbnail": "assets/card/ITPO_MANA_03.webp"
    },
    {
        "title": "ITPO_SPEED",
        "name": "Mikstura szybkości",
        "opis": "Mikstura która pobudzi cię do działania.",
        "mainFlag": "ITEM_CAT_POTION",
        "instance": "ITPO_SPEED",
        "instancesaga3": "ITPO_GS_13",
        "category": "Potion",
        "weight": "0,2",
        "durability": "BRAK",
        "uses": "1",
        "staminaPerHit": "0",
        "hpPerHit": "0",
        "manaPerHit": "0",
        "stamina": "0",
        "hp": "0",
        "mana": "0",
        "dmgType": "BRAK",
        "dmg": "BRAK",
        "range": "BRAK",
        "strength": "BRAK",
        "dexterity": "BRAK",
        "intelligence": "BRAK",
        "magicCircle": "BRAK",
        "manaCost": "BRAK",
        "resistance_blunt": "BRAK",
        "resistance_projectile": "BRAK",
        "resistance_slash": "BRAK",
        "resistance_magic": "BRAK",
        "resistance_fire": "BRAK",
        "resistance_fall": "BRAK",
        "modelNazwa": "ItPo_Speed.3ds",
        "tier": "T4",
        "expirationTime": "BRAK",
        "plik": "potions",
        "profession": "Alchemik",
        "model": "assets/models/ITPO_SPEED.glb",
        "thumbnail": "assets/card/ITPO_SPEED.webp"
    },
    {
        "title": "ITPO_HEALTH_03",
        "name": "Pełnia życia",
        "opis": "Jedna z mikstur leczących",
        "mainFlag": "ITEM_CAT_POTION",
        "instance": "itpo_health_03",
        "instancesaga3": "ITPO_GS_14",
        "category": "Potion",
        "weight": "0,2",
        "durability": "BRAK",
        "uses": "1",
        "staminaPerHit": "0",
        "hpPerHit": "50",
        "manaPerHit": "0",
        "stamina": "0",
        "hp": "50",
        "mana": "0",
        "dmgType": "BRAK",
        "dmg": "BRAK",
        "range": "BRAK",
        "strength": "BRAK",
        "dexterity": "BRAK",
        "intelligence": "BRAK",
        "magicCircle": "BRAK",
        "manaCost": "BRAK",
        "resistance_blunt": "BRAK",
        "resistance_projectile": "BRAK",
        "resistance_slash": "BRAK",
        "resistance_magic": "BRAK",
        "resistance_fire": "BRAK",
        "resistance_fall": "BRAK",
        "modelNazwa": "ItPo_Health_03.3ds",
        "tier": "T4",
        "expirationTime": "BRAK",
        "plik": "potions",
        "profession": "Alchemik",
        "model": "assets/models/ITPO_HEALTH_03.glb",
        "thumbnail": "assets/card/ITPO_HEALTH_03.webp"
    },
    {
        "title": "ITPO_MANA_03",
        "name": "Pełnia many",
        "opis": "Jedna z mikstur odnawiających energię duchową",
        "mainFlag": "ITEM_CAT_POTION",
        "instance": "ItPo_Mana_03",
        "instancesaga3": "ITPO_GS_15",
        "category": "Potion",
        "weight": "0,2",
        "durability": "BRAK",
        "uses": "1",
        "staminaPerHit": "0",
        "hpPerHit": "0",
        "manaPerHit": "50",
        "stamina": "0",
        "hp": "0",
        "mana": "50",
        "dmgType": "BRAK",
        "dmg": "BRAK",
        "range": "BRAK",
        "strength": "BRAK",
        "dexterity": "BRAK",
        "intelligence": "BRAK",
        "magicCircle": "BRAK",
        "manaCost": "BRAK",
        "resistance_blunt": "BRAK",
        "resistance_projectile": "BRAK",
        "resistance_slash": "BRAK",
        "resistance_magic": "BRAK",
        "resistance_fire": "BRAK",
        "resistance_fall": "BRAK",
        "modelNazwa": "ItPo_Mana_03.3ds",
        "tier": "T4",
        "expirationTime": "BRAK",
        "plik": "potions",
        "profession": "Alchemik",
        "model": "assets/models/ITPO_MANA_03.glb",
        "thumbnail": "assets/card/ITPO_MANA_03.webp"
    },
    {
        "title": "ITPO_PERM_STR",
        "name": "Mikstura Trolla",
        "opis": "Mikstura znana z tego iż zamienia twoją wątłą ludzką skórę, w coś przypominającą skórę trolla.",
        "mainFlag": "ITEM_CAT_POTION",
        "instance": "ItPo_Addon_Geist_01",
        "instancesaga3": "ITPO_GS_16",
        "category": "Potion",
        "weight": "0,2",
        "durability": "BRAK",
        "uses": "1",
        "staminaPerHit": "0",
        "hpPerHit": "0",
        "manaPerHit": "0",
        "stamina": "0",
        "hp": "0",
        "mana": "0",
        "dmgType": "BRAK",
        "dmg": "BRAK",
        "range": "BRAK",
        "strength": "BRAK",
        "dexterity": "BRAK",
        "intelligence": "BRAK",
        "magicCircle": "BRAK",
        "manaCost": "BRAK",
        "resistance_blunt": "BRAK",
        "resistance_projectile": "BRAK",
        "resistance_slash": "BRAK",
        "resistance_magic": "BRAK",
        "resistance_fire": "BRAK",
        "resistance_fall": "BRAK",
        "modelNazwa": "ItPo_Perm_STR.3ds",
        "tier": "T5",
        "expirationTime": "BRAK",
        "plik": "potions",
        "profession": "Alchemik",
        "model": "assets/models/ITPO_PERM_STR.glb",
        "thumbnail": "assets/card/ITPO_PERM_STR.webp"
    },
    {
        "title": "ITPO_PERM_HEALTH",
        "name": "Eliksir Ochronny",
        "opis": "Przydatna przy magicznych eksperymentach.",
        "mainFlag": "ITEM_CAT_POTION",
        "instance": "itpo_perm_health",
        "instancesaga3": "ITPO_GS_17",
        "category": "Potion",
        "weight": "0,2",
        "durability": "BRAK",
        "uses": "1",
        "staminaPerHit": "0",
        "hpPerHit": "0",
        "manaPerHit": "0",
        "stamina": "0",
        "hp": "0",
        "mana": "0",
        "dmgType": "BRAK",
        "dmg": "BRAK",
        "range": "BRAK",
        "strength": "BRAK",
        "dexterity": "BRAK",
        "intelligence": "BRAK",
        "magicCircle": "BRAK",
        "manaCost": "BRAK",
        "resistance_blunt": "BRAK",
        "resistance_projectile": "BRAK",
        "resistance_slash": "BRAK",
        "resistance_magic": "BRAK",
        "resistance_fire": "BRAK",
        "resistance_fall": "BRAK",
        "modelNazwa": "ItPo_Perm_Health.3ds",
        "tier": "T5",
        "expirationTime": "BRAK",
        "plik": "potions",
        "profession": "Alchemik",
        "model": "assets/models/ITPO_PERM_HEALTH.glb",
        "thumbnail": "assets/card/ITPO_PERM_HEALTH.webp"
    },
    {
        "title": "ITPO_PERM_DEX",
        "name": "Napój z pełzaczy",
        "opis": "Specjalny napój odnawiający energię życiową i duchową. Pozwala wyzwolić wizje.",
        "mainFlag": "ITEM_CAT_POTION",
        "instance": "ItPo_Perm_Dex",
        "instancesaga3": "ITPO_GS_18",
        "category": "Potion",
        "weight": "0,2",
        "durability": "BRAK",
        "uses": "1",
        "staminaPerHit": "0",
        "hpPerHit": "0",
        "manaPerHit": "0",
        "stamina": "0",
        "hp": "0",
        "mana": "0",
        "dmgType": "BRAK",
        "dmg": "BRAK",
        "range": "BRAK",
        "strength": "BRAK",
        "dexterity": "BRAK",
        "intelligence": "BRAK",
        "magicCircle": "BRAK",
        "manaCost": "BRAK",
        "resistance_blunt": "BRAK",
        "resistance_projectile": "BRAK",
        "resistance_slash": "BRAK",
        "resistance_magic": "BRAK",
        "resistance_fire": "BRAK",
        "resistance_fall": "BRAK",
        "modelNazwa": "ItPo_Perm_DEX.3ds",
        "tier": "T5",
        "expirationTime": "BRAK",
        "plik": "potions",
        "profession": "Alchemik",
        "model": "assets/models/ITPO_PERM_DEX.glb",
        "thumbnail": "assets/card/ITPO_PERM_DEX.webp"
    }
]